mantarray_file_manager/__init__.py
mantarray_file_manager/constants.py
mantarray_file_manager/exceptions.py
mantarray_file_manager/file_writer.py
mantarray_file_manager/files.py
mantarray_file_manager-1.0.1.dist-info/LICENSE
mantarray_file_manager-1.0.1.dist-info/METADATA
mantarray_file_manager-1.0.1.dist-info/WHEEL
mantarray_file_manager-1.0.1.dist-info/top_level.txt
mantarray_file_manager-1.0.1.dist-info/RECORD
