Metadata-Version: 2.1
Name: mantarray-file-manager
Version: 1.0.1
Summary: Finds and opens Mantarray files.
Home-page: https://github.com/CuriBio/mantarray-file-manager
Author: Curi Bio
Author-email: contact@curibio.com
License: MIT
Platform: UNKNOWN
Classifier: Development Status :: 1 - Planning
Classifier: Intended Audience :: Science/Research
Classifier: License :: OSI Approved :: MIT License
Classifier: Programming Language :: Python
Classifier: Programming Language :: Python :: 3
Classifier: Programming Language :: Python :: 3.7
Classifier: Programming Language :: Python :: 3.8
Classifier: Programming Language :: Python :: 3.9
Classifier: Topic :: Scientific/Engineering
License-File: LICENSE
Requires-Dist: h5py (>=2.10.0)
Requires-Dist: nptyping (>=1.3.0)
Requires-Dist: numpy (>=1.20.2)
Requires-Dist: stdlib-utils (>=0.2.1)
Requires-Dist: semver (>=2.10.2)
Requires-Dist: immutable-data-validation (>=0.2.1)
Requires-Dist: immutabledict (>=1.1.0)
